fasma/core/boxes.py
fasma/core/df_filters.py
fasma/core/df_generators.py
fasma/core/file_compressor.py
fasma/core/file_reader.py
fasma/core/functional.py
fasma/core/keyword_trie.py
fasma/core/messages.py
fasma/core/plotter.py
fasma/core/spectrum.py
fasma/gaussian/parse_basic.py
fasma/gaussian/parse_cas.py
fasma/gaussian/parse_excitation.py
fasma/gaussian/parse_functions.py
fasma/gaussian/parse_gaussian.py
fasma/gaussian/parse_matrices.py
fasma/gaussian/parse_pop.py
fasma/gaussian/parse_td.py
fasma-0.0.1.dist-info/LICENSE
fasma-0.0.1.dist-info/METADATA
fasma-0.0.1.dist-info/WHEEL
fasma-0.0.1.dist-info/top_level.txt
fasma-0.0.1.dist-info/RECORD
