Metadata-Version: 2.1
Name: fasma
Version: 0.0.1
Summary: Analyzer for computational chemistry outputs
Author-email: Kevin Hoang <khoang89@uw.edu>
License: MIT License
Project-URL: Homepage, https://github.com/xsligroup/fasma
Keywords: chemistry,gaussian,chronus,spectra
Classifier: License :: OSI Approved :: MIT License
Classifier: Programming Language :: Python
Classifier: Programming Language :: Python :: 3
Classifier: Development Status :: 3 - Alpha
Classifier: Intended Audience :: Science/Research
Classifier: Topic :: Scientific/Engineering :: Chemistry
Requires-Python: >=3.9
License-File: LICENSE
Requires-Dist: numpy >=1.23.0
Requires-Dist: matplotlib >=3.5.2
Requires-Dist: scipy >=1.9.1
Requires-Dist: pandas >=1.4.3
Provides-Extra: data
Requires-Dist: notebook >=6.5.4 ; extra == 'data'
Requires-Dist: jupyter ; extra == 'data'
